{
	"1359275248": { "Name": "Kills", "Type": "Apex", "Emote": "" },
	"1927694151": { "Name": "Winning Kills", "Type": "Apex", "Emote": "" },
	"604873453": { "Name": "Kills as Kill Leader", "Type": "Apex", "Emote": "" },
	"1416294179": { "Name": "Damage", "Type": "Apex", "Emote": "" },
	"671033689": { "Name": "Headshots", "Type": "Apex", "Emote": "" },
	"1461345513": { "Name": "Finishers", "Type": "Apex", "Emote": "" },
	"1391825387": { "Name": "Revives", "Type": "Apex", "Emote": "" },
	"2142987015": { "Name": "Games Played", "Type": "Apex", "Emote": "" },
	"2056807187": { "Name": "Wins with Full Squad Alive", "Type": "Apex", "Emote": "" },
	"1244785447": { "Name": "Times Placed Top 3", "Type": "Apex", "Emote": "" },
	"888068016": { "Name": "AR Kills", "Type": "Apex", "Emote": "" },
	"39760556": { "Name": "LMG Kills", "Type": "Apex", "Emote": "" },
	"489250900": { "Name": "Marksman Kills", "Type": "Apex", "Emote": "" },
	"488738688": { "Name": "Pistol Kills", "Type": "Apex", "Emote": "" },
	"1989663384": { "Name": "Shotgun Kills", "Type": "Apex", "Emote": "" },
	"1833068474": { "Name": "SMG Kills", "Type": "Apex", "Emote": "" },
	"1502057616": { "Name": "Sniper Kills", "Type": "Apex", "Emote": "" },
	"1573771376": { "Name": "Care Package Weapon Kills", "Type": "Apex", "Emote": "" },
	"779225198": { "Name": "Wins", "Type": "Arenas", "Emote": "" },
	"2000402315": { "Name": "Kills", "Type": "Arenas", "Emote": "" },
	"1396395841": { "Name": "Damage", "Type": "Arenas", "Emote": "" },
	"42379430": { "Name": "Loot Pinged Through Walls", "Type": "", "Emote": "" },
	"1370374388": { "Name": "Meters Teleported", "Type": "", "Emote": "" },
	"842827023": { "Name": "Loot Taken by Allies", "Type": "", "Emote": "" },
	"1965136863": { "Name": "Wins", "Type": "S5 Apex", "Emote": "Season_5" },
	"1128486290": { "Name": "Kills", "Type": "S5 Apex", "Emote": "Season_5" },
	"989931955": { "Name": "Kills", "Type": "Apex", "Emote": "" },
	"1238194389": { "Name": "Wins", "Type": "Apex", "Emote": "" },
	"696706348": { "Name": "Damage", "Type": "Apex", "Emote": "" },
	"303840555": { "Name": "Wins", "Type": "S6 Apex", "Emote": "Season_6" },
	"1695573704": { "Name": "Kills", "Type": "S6 Apex", "Emote": "Season_6" },
	"1411790226": { "Name": "Wins", "Type": "S7 Apex", "Emote": "Season_7" },
	"1635648258": { "Name": "Kills", "Type": "S7 Apex", "Emote": "Season_7" },
	"1632149633": { "Name": "Kills", "Type": "S8 Apex", "Emote": "Season_8" },
	"917447046": { "Name": "Wins", "Type": "S8 Apex", "Emote": "Season_8" },
	"728519239": { "Name": "Kills", "Type": "S9 Apex", "Emote": "Season_9" },
	"923318986": { "Name": "Wins", "Type": "S9 Apex", "Emote": "Season_9" },
	"1059321785": { "Name": "Kills", "Type": "S10 Apex", "Emote": "Season_10" },
	"1080261994": { "Name": "Wins", "Type": "S10 Apex", "Emote": "Season_10" },
	"697656212": { "Name": "Wins", "Type": "Apex", "Emote": "" },
	"734646341": { "Name": "Kills", "Type": "Apex", "Emote": "" },
	"984197827": { "Name": "Damage", "Type": "Apex", "Emote": "" },
	"918601344": { "Name": "Kills", "Type": "S11 Apex", "Emote": "Season_11" },
	"1115965990": { "Name": "Wins", "Type": "S11 Apex", "Emote": "Season_11" },
	"1230234494": { "Name": "Kills", "Type": "S12 Apex", "Emote": "Season_12" },
	"475335530": { "Name": "Wins", "Type": "S12 Apex", "Emote": "Season_12" },
	"1441758387": { "Name": "Damage", "Type": "Apex", "Emote": "" },
	"938912688": { "Name": "Kills", "Type": "Apex", "Emote": "" },
	"718979163": { "Name": "Wins", "Type": "Apex", "Emote": "" },
	"1657387249": { "Name": "Kills", "Type": "S13 Apex", "Emote": "Season_13" },
	"924800679": { "Name": "Wins", "Type": "S13 Apex", "Emote": "Season_13" }
}
