{
	"1730527550": { "Name": "Kills", "Type": "Apex", "Emote": "" },
	"1061520566": { "Name": "Winning Kills", "Type": "Apex", "Emote": "" },
	"2015631597": { "Name": "Kills as Kill Leader", "Type": "Apex", "Emote": "" },
	"2014839975": { "Name": "Damage", "Type": "Apex", "Emote": "" },
	"240059894": { "Name": "Headshots", "Type": "Apex", "Emote": "" },
	"830747811": { "Name": "Finishers", "Type": "Apex", "Emote": "" },
	"1539065824": { "Name": "Revives", "Type": "Apex", "Emote": "" },
	"155530518": { "Name": "Games Played", "Type": "Apex", "Emote": "" },
	"1654975970": { "Name": "Wins with Full Squad Alive", "Type": "Apex", "Emote": "" },
	"1996756430": { "Name": "Times Placed Top 3", "Type": "Apex", "Emote": "" },
	"1019716863": { "Name": "AR Kills", "Type": "Apex", "Emote": "" },
	"746316731": { "Name": "LMG Kills", "Type": "Apex", "Emote": "" },
	"625006618": { "Name": "Marksman Kills", "Type": "Apex", "Emote": "" },
	"919756330": { "Name": "Pistol Kills", "Type": "Apex", "Emote": "" },
	"1914914556": { "Name": "Shotgun Kills", "Type": "Apex", "Emote": "" },
	"1568462105": { "Name": "SMG Kills", "Type": "Apex", "Emote": "" },
	"352244005": { "Name": "Sniper Kills", "Type": "Apex", "Emote": "" },
	"137953061": { "Name": "Care Package Weapon Kills", "Type": "Apex", "Emote": "" },
	"1633313961": { "Name": "Wins", "Type": "Arenas", "Emote": "" },
	"586137363": { "Name": "Kills", "Type": "Arenas", "Emote": "" },
	"1024169352": { "Name": "Damage", "Type": "Arenas", "Emote": "" },
	"230838395": { "Name": "Encore: Executions Escaped", "Type": "", "Emote": "" },
	"635416044": { "Name": "Decoys Created", "Type": "", "Emote": "" },
	"884674356": { "Name": "Bamboozles", "Type": "", "Emote": "" },
	"1179829977": { "Name": "Wins", "Type": "S1 Apex", "Emote": "Season_1" },
	"689606126": { "Name": "Kills", "Type": "S1 Apex", "Emote": "Season_1" },
	"1361602069": { "Name": "Damage", "Type": "S1 Apex", "Emote": "Season_1" },
	"1500066309": { "Name": "Wins", "Type": "S2 Apex", "Emote": "Season_2" },
	"1136168729": { "Name": "Wins", "Type": "S3 Apex", "Emote": "Season_3" },
	"1760707531": { "Name": "Wins", "Type": "S4 Apex", "Emote": "Season_4" },
	"533334508": { "Name": "Wins", "Type": "S5 Apex", "Emote": "Season_5" },
	"1469409777": { "Name": "Kills", "Type": "S5 Apex", "Emote": "Season_5" },
	"2112883966": { "Name": "Wins", "Type": "S6 Apex", "Emote": "Season_6" },
	"25920551": { "Name": "Kills", "Type": "S6 Apex", "Emote": "Season_6" },
	"244408465": { "Name": "Wins", "Type": "S7 Apex", "Emote": "Season_7" },
	"1307217201": { "Name": "Kills", "Type": "S7 Apex", "Emote": "Season_7" },
	"710621083": { "Name": "Kills", "Type": "Apex", "Emote": "" },
	"803607498": { "Name": "Wins", "Type": "Apex", "Emote": "" },
	"965890515": { "Name": "Damage", "Type": "Apex", "Emote": "" },
	"273457735": { "Name": "Wins", "Type": "Apex", "Emote": "" },
	"821300195": { "Name": "Kills", "Type": "S8 Apex", "Emote": "Season_8" },
	"1637854906": { "Name": "Wins", "Type": "S8 Apex", "Emote": "Season_8" },
	"1205462478": { "Name": "Kills", "Type": "S9 Apex", "Emote": "Season_9" },
	"1611697240": { "Name": "Wins", "Type": "S9 Apex", "Emote": "Season_9" },
	"1098864047": { "Name": "Kills", "Type": "S10 Apex", "Emote": "Season_10" },
	"828578924": { "Name": "Wins", "Type": "S10 Apex", "Emote": "Season_10" },
	"519883496": { "Name": "Kills", "Type": "S11 Apex", "Emote": "Season_11" },
	"1675524255": { "Name": "Wins", "Type": "S11 Apex", "Emote": "Season_11" },
	"687317347": { "Name": "Kills", "Type": "Apex", "Emote": "" },
	"1445061412": { "Name": "Wins", "Type": "Apex", "Emote": "" },
	"438661956": { "Name": "Damage", "Type": "Apex", "Emote": "" },
	"1220440075": { "Name": "Kills", "Type": "S12 Apex", "Emote": "Season_12" },
	"115829082": { "Name": "Wins", "Type": "S12 Apex", "Emote": "Season_12" },
	"988580202": { "Name": "Kills", "Type": "Apex", "Emote": "" },
	"1446203982": { "Name": "Wins", "Type": "Apex", "Emote": "" },
	"464598481": { "Name": "Damage", "Type": "Apex", "Emote": "" },
	"1106880670": { "Name": "Kills", "Type": "S13 Apex", "Emote": "Season_13" },
	"1156613013": { "Name": "Wins", "Type": "S13 Apex", "Emote": "Season_13" },
	"409883304": { "Name": "Kills", "Type": "Apex", "Emote": "" },
	"1173787579": { "Name": "Bamboozles", "Type": "", "Emote": "" },
	"1000328278": { "Name": "Damage", "Type": "Apex", "Emote": "" },
	"9455320": { "Name": "Kills", "Type": "S14 Apex", "Emote": "Season_14" },
	"919611500": { "Name": "Wins", "Type": "S14 Apex", "Emote": "Season_14" }
}
